cantoroman/__init__.py
cantoroman/canto.py
cantoroman/__pycache__/__init__.cpython-37.pyc
cantoroman/__pycache__/__init__.cpython-38.pyc
cantoroman/__pycache__/canto.cpython-37.pyc
cantoroman/__pycache__/canto.cpython-38.pyc
cantoroman/data/charToLshk.json
cantoroman/data/charToRoman.json
cantoroman/data/charToYale.json
cantoroman/data/lshkToChar.json
cantoroman/data/romanToChar.json
cantoroman/data/yaleToChar.json
cantonese_romanisation-1.0.5.dist-info/METADATA
cantonese_romanisation-1.0.5.dist-info/WHEEL
cantonese_romanisation-1.0.5.dist-info/top_level.txt
cantonese_romanisation-1.0.5.dist-info/RECORD
