Metadata-Version: 2.1
Name: cantonese-romanisation
Version: 1.0.5
Summary: Library for mapping Chinese character to Hong Kong Government Cantonese Romanisation, Pingyam (Yale or LSHK)
Author: Chun Law (chunalw)
Author-email: <chunlaw@rocketmail.com.com>
Keywords: pinyin,cantonese,pingyam,hong kong government cantonese romanisation,romanisation,romanization
Classifier: Development Status :: 5 - Production/Stable
Classifier: Intended Audience :: Developers
Classifier: Programming Language :: Python :: 3
Classifier: License :: OSI Approved :: MIT License
Classifier: Operating System :: Unix
Classifier: Operating System :: MacOS :: MacOS X
Classifier: Operating System :: Microsoft :: Windows
